yanlp/__init__.py
yanlp/test.py
yanlp-0.0.1.dist-info/LICENSE
yanlp-0.0.1.dist-info/METADATA
yanlp-0.0.1.dist-info/WHEEL
yanlp-0.0.1.dist-info/top_level.txt
yanlp-0.0.1.dist-info/RECORD
